{
    "project": {
        "name": "Hill Demo (Backsight)",
        "rows": 8,
        "cols": 8,
        "spacing": 10,
        "units": "m",
        "contourInterval": 1,
        "majorMultiplier": 5,
        "dataType": "backsight",
        "benchmark": 100.000,
        "backsight": 1000.0,
        "hi": 110.000
    },
    "grid": [
        [
            105.2,
            105.8,
            106.5,
            107.1,
            107.4,
            107.2,
            106.8,
            106.1
        ],
        [
            105.9,
            107.2,
            108.6,
            109.8,
            110.2,
            109.7,
            108.4,
            107.3
        ],
        [
            106.7,
            108.8,
            111.4,
            113.5,
            114.2,
            113.1,
            110.8,
            108.2
        ],
        [
            107.4,
            110.5,
            114.2,
            117.8,
            118.5,
            116.4,
            112.5,
            109.1
        ],
        [
            107.6,
            110.8,
            114.6,
            118.2,
            119.1,
            116.8,
            112.8,
            109.4
        ],
        [
            107.2,
            109.4,
            111.8,
            114.5,
            115.2,
            113.4,
            110.2,
            108.5
        ],
        [
            106.4,
            107.5,
            108.9,
            110.2,
            110.8,
            109.8,
            108.5,
            107.2
        ],
        [
            105.5,
            106.1,
            106.8,
            107.5,
            108.1,
            107.8,
            107.2,
            106.4
        ]
    ],
    "fsGrid": [
        [
            480,
            420,
            350,
            290,
            260,
            280,
            320,
            390
        ],
        [
            410,
            280,
            140,
            20,
            -20,
            30,
            160,
            270
        ],
        [
            330,
            120,
            -140,
            -350,
            -420,
            -310,
            -80,
            180
        ],
        [
            260,
            -50,
            -420,
            -780,
            -850,
            -640,
            -250,
            90
        ],
        [
            240,
            -80,
            -460,
            -820,
            -910,
            -680,
            -280,
            60
        ],
        [
            280,
            60,
            -180,
            -450,
            -520,
            -340,
            -20,
            150
        ],
        [
            360,
            250,
            110,
            -20,
            -80,
            20,
            150,
            280
        ],
        [
            450,
            390,
            320,
            250,
            190,
            220,
            280,
            360
        ]
    ]
}